{
  "hash": "e6d948a4",
  "configHash": "13200f1d",
  "lockfileHash": "fd016d17",
  "browserHash": "b2965f02",
  "optimized": {
    "react/jsx-dev-runtime": {
      "src": "../../node_modules/react/jsx-dev-runtime.js",
      "file": "react_jsx-dev-runtime.js",
      "fileHash": "a2df1f20",
      "needsInterop": true
    },
    "react": {
      "src": "../../node_modules/react/index.js",
      "file": "react.js",
      "fileHash": "67691fbf",
      "needsInterop": true
    },
    "react-dom/client": {
      "src": "../../node_modules/react-dom/client.js",
      "file": "react-dom_client.js",
      "fileHash": "ff08632d",
      "needsInterop": true
    },
    "react-router-dom": {
      "src": "../../node_modules/react-router-dom/dist/index.mjs",
      "file": "react-router-dom.js",
      "fileHash": "74409ae5",
      "needsInterop": false
    },
    "@tanstack/react-query": {
      "src": "../../node_modules/@tanstack/react-query/build/modern/index.js",
      "file": "@tanstack_react-query.js",
      "fileHash": "a0a24f6d",
      "needsInterop": false
    },
    "@radix-ui/react-slot": {
      "src": "../../node_modules/@radix-ui/react-slot/dist/index.mjs",
      "file": "@radix-ui_react-slot.js",
      "fileHash": "c38c98ff",
      "needsInterop": false
    },
    "class-variance-authority": {
      "src": "../../node_modules/class-variance-authority/dist/index.mjs",
      "file": "class-variance-authority.js",
      "fileHash": "60ab04ff",
      "needsInterop": false
    },
    "lucide-react": {
      "src": "../../node_modules/lucide-react/dist/esm/lucide-react.js",
      "file": "lucide-react.js",
      "fileHash": "5514af1c",
      "needsInterop": false
    }
  },
  "chunks": {
    "chunk-AU2MKR2E": {
      "file": "chunk-AU2MKR2E.js"
    },
    "chunk-7WO645K6": {
      "file": "chunk-7WO645K6.js"
    },
    "chunk-VX2H6PUQ": {
      "file": "chunk-VX2H6PUQ.js"
    },
    "chunk-G3PMV62Z": {
      "file": "chunk-G3PMV62Z.js"
    }
  }
}